{"cameraMode":{"drawMode":0,"name":"Shaded","section":"Shading Mode"},"sceneLighting":true,"audioPlay":false,"sceneViewState":{"showFog":true,"showMaterialUpdate":false,"showSkybox":true,"showFlares":true,"showImageEffects":true,"showParticleSystems":true,"showVisualEffectGraphs":true,"m_FxEnabled":true},"in2DMode":false,"pivot":{"x":-1.8937820196151734,"y":-2.09122371673584,"z":-7.274720191955566},"rotation":{"x":0.410670667886734,"y":0.10656532645225525,"z":-0.0483953021466732,"w":0.9042342901229858},"size":2.7510263919830324,"orthographic":false}